<?xml version="1.0" encoding="utf-8" ?>
<dwsync>
<file name="glyphicons-halflings-regular.woff" server="72.167.2.1/schmittowing/" local="130646820443823300" remote="130647012000000000" Dst="0" />
<file name="glyphicons-halflings-regular.ttf" server="72.167.2.1/schmittowing/" local="130646820443763257" remote="130647012000000000" Dst="0" />
<file name="glyphicons-halflings-regular.eot" server="72.167.2.1/schmittowing/" local="130646820443593116" remote="130647012000000000" Dst="0" />
<file name="glyphicons-halflings-regular.svg" server="72.167.2.1/schmittowing/" local="130646820443683180" remote="130647012000000000" Dst="0" />
<file name="glyphicons-halflings-regular.eot" server="72.167.2.1/henderson/" local="130674632362318883" remote="130674660600000000" Dst="0" />
<file name="glyphicons-halflings-regular.svg" server="72.167.2.1/henderson/" local="130674632362408955" remote="130674660600000000" Dst="0" />
<file name="glyphicons-halflings-regular.ttf" server="72.167.2.1/henderson/" local="130674632362509002" remote="130674660600000000" Dst="0" />
<file name="glyphicons-halflings-regular.woff" server="72.167.2.1/henderson/" local="130674632362579242" remote="130674660600000000" Dst="0" />
<file name="glyphicons-halflings-regular.eot" server="107.180.41.85/henderson/" local="130687557135133958" remote="131079630600000000" Dst="2" />
<file name="glyphicons-halflings-regular.svg" server="107.180.41.85/henderson/" local="130687557135213999" remote="131079630600000000" Dst="2" />
<file name="glyphicons-halflings-regular.ttf" server="107.180.41.85/henderson/" local="130687557135294056" remote="131079630600000000" Dst="2" />
<file name="glyphicons-halflings-regular.woff" server="107.180.41.85/henderson/" local="130687557135354098" remote="131079630600000000" Dst="2" />
</dwsync>